dir_audit/__init__.py
dir_audit/__main__.py
dir_audit/check.py
dir_audit/make.py
dir_audit/parser.py
dir_audit-0.3.2.dist-info/LICENSE
dir_audit-0.3.2.dist-info/METADATA
dir_audit-0.3.2.dist-info/WHEEL
dir_audit-0.3.2.dist-info/RECORD
