Metadata-Version: 2.1
Name: dir-audit
Version: 0.3.2
Summary: Directory tree audit tool
Home-page: https://github.com/deltodon/dir-audit
License: GPL-3.0
Keywords: Directory,Tree,Search
Author: Jiri Klic
Author-email: web@jiriklic.com
Requires-Python: >=3.8,<4.0
Classifier: Development Status :: 3 - Alpha
Classifier: Intended Audience :: Developers
Classifier: License :: OSI Approved :: GNU General Public License v3 (GPLv3)
Classifier: Programming Language :: Python :: 3
Classifier: Programming Language :: Python :: 3.8
Classifier: Programming Language :: Python :: 3.9
Classifier: Programming Language :: Python :: 3.10
Classifier: Programming Language :: Python :: 3.11
Classifier: Programming Language :: Python :: 3.12
Classifier: Programming Language :: Python :: Implementation :: CPython
Requires-Dist: directory-tree (>=1.0.0,<2.0.0)
Project-URL: Repository, https://github.com/deltodon/dir-audit
